thousandeyes_sdk/emulation/__init__.py
thousandeyes_sdk/emulation/py.typed
thousandeyes_sdk/emulation/api/__init__.py
thousandeyes_sdk/emulation/api/emulation_api.py
thousandeyes_sdk/emulation/models/__init__.py
thousandeyes_sdk/emulation/models/emulated_device.py
thousandeyes_sdk/emulation/models/emulated_device_category.py
thousandeyes_sdk/emulation/models/emulated_device_response.py
thousandeyes_sdk/emulation/models/emulated_device_responses.py
thousandeyes_sdk/emulation/models/error.py
thousandeyes_sdk/emulation/models/expand_emulated_device_options.py
thousandeyes_sdk/emulation/models/link.py
thousandeyes_sdk/emulation/models/self_links.py
thousandeyes_sdk/emulation/models/unauthorized_error.py
thousandeyes_sdk/emulation/models/user_agent.py
thousandeyes_sdk/emulation/models/user_agents.py
thousandeyes_sdk_emulation-2.23.0.dist-info/licenses/LICENSE
thousandeyes_sdk_emulation-2.23.0.dist-info/licenses/NOTICE
thousandeyes_sdk_emulation-2.23.0.dist-info/METADATA
thousandeyes_sdk_emulation-2.23.0.dist-info/WHEEL
thousandeyes_sdk_emulation-2.23.0.dist-info/top_level.txt
thousandeyes_sdk_emulation-2.23.0.dist-info/RECORD
